easier_gpt-0.2.1.dist-info/licenses/LICENSE
openai_wrapper/__init__.py
openai_wrapper/assistant.py
openai_wrapper/tempCodeRunnerFile.py
easier_gpt-0.2.1.dist-info/METADATA
easier_gpt-0.2.1.dist-info/WHEEL
easier_gpt-0.2.1.dist-info/top_level.txt
easier_gpt-0.2.1.dist-info/RECORD
