Metadata-Version: 2.4
Name: easier-gpt
Version: 0.2.1
Summary: Utilities for orchestrating OpenAI chat, tool calling, search, audio, and images from one helper package.
Author-email: Advik Mathur <pranit.advik@gmail.com>
License: Apache-2.0
Project-URL: Homepage, https://github.com/Adpros7/easier-gpt
Project-URL: Repository, https://github.com/Adpros7/easier-gpt
Project-URL: Documentation, https://github.com/Adpros7/easier-gpt
Project-URL: Issues, https://github.com/Adpros7/easier-gpt/issues
Keywords: openai,assistant,chat,responses,audio,images,vector
Classifier: Development Status :: 4 - Beta
Classifier: Intended Audience :: Developers
Classifier: License :: OSI Approved :: Apache Software License
Classifier: Programming Language :: Python :: 3
Classifier: Programming Language :: Python :: 3.10
Classifier: Programming Language :: Python :: 3.11
Classifier: Programming Language :: Python :: 3.12
Classifier: Programming Language :: Python :: 3.13
Classifier: Topic :: Software Development :: Libraries :: Python Modules
Requires-Python: >=3.10
License-File: LICENSE
Requires-Dist: openai>=1.43.0
Requires-Dist: typing_extensions>=4.7.0
Requires-Dist: pydantic>=2.0.0
Requires-Dist: simpleaudio>=1.0.4
Requires-Dist: openai-stt>=0.1.0
Provides-Extra: function-tools
Requires-Dist: ez-openai>=0.1.5; extra == "function-tools"
Provides-Extra: speech-models
Requires-Dist: whisper>=1.0; extra == "speech-models"
Dynamic: license-file
